{
    "global": {
        "curse": true,
        "hitokoto": true,
        "roll": true,
        "rcnb": true,
        "setu": true
    },
    "330616602": {
        "curse": true,
        "hitokoto": true,
        "setu": true,
        "roll": true,
        "rcnb": true
    },
    "516729280": {
        "curse": true,
        "hitokoto": true,
        "setu": true,
        "roll": true,
        "rcnb": true
    },
    "1126435961": {
        "curse": true,
        "hitokoto": true,
        "setu": true,
        "roll": true,
        "rcnb": true
    },
    "879471303": {
        "curse": true,
        "hitokoto": true,
        "setu": true,
        "roll": true,
        "rcnb": true
    },
    "663588449": {
        "curse": true,
        "hitokoto": true,
        "setu": true,
        "roll": true,
        "rcnb": true
    },
    "672076603": {
        "curse": true,
        "hitokoto": true,
        "setu": true,
        "roll": true,
        "rcnb": true
    },
    "1128059355": {
        "curse": true,
        "hitokoto": true,
        "setu": true,
        "roll": true,
        "rcnb": true
    },
    "567297659": {
        "curse": true,
        "hitokoto": true,
        "setu": true,
        "roll": true,
        "rcnb": true
    },
    "921925032": {
        "curse": true,
        "hitokoto": true,
        "setu": true,
        "roll": true,
        "rcnb": true
    },
    "null": {
        "curse": true,
        "hitokoto": true,
        "setu": true,
        "roll": true,
        "rcnb": true
    },
    "652116841": {
        "curse": true,
        "hitokoto": true,
        "setu": true,
        "roll": true,
        "rcnb": true
    },
    "1126435961": {
        "curse": true,
        "hitokoto": true,
        "setu": true,
        "roll": true,
        "rcnb": true
    }
}